dex_k8s_client/__init__.py
dex_k8s_client/bindings.py
dex_k8s_client/bindings_test.py
dex_k8s_client/client.py
dex_k8s_client/client_test.py
dex_k8s_client/settings.py
dex_k8s_client/settings_test.py
dex_k8s_client/dexidp/__init__.py
dex_k8s_client/dexidp/dex/__init__.py
dex_k8s_client/dexidp/dex/api/__init__.py
dex_k8s_client/dexidp/dex/api/v2_14_0_pb2.py
dex_k8s_client/dexidp/dex/api/v2_14_0_pb2_grpc.py
dex_k8s_client/dexidp/dex/api/v2_14_0_pb2_test_fields.py
dex_k8s_client/k8s/__init__.py
dex_k8s_client/k8s/cluster.py
dex_k8s_client/k8s/cluster_test.py
dex_k8s_client/k8s/connector.py
dex_k8s_client/k8s/connector_test.py
dex_k8s_client/k8s/kubeconfig.py
dex_k8s_client/k8s/kubeconfig_test.py
dex_k8s_client/oauth2/__init__.py
dex_k8s_client/oauth2/client.py
dex_k8s_client/oauth2/client_test.py
dex_k8s_client/oauth2/parser.py
dex_k8s_client/oauth2/parser_test.py
dex_k8s_client/oauth2/token.py
dex_k8s_client-0.1.1.dist-info/LICENSE
dex_k8s_client-0.1.1.dist-info/METADATA
dex_k8s_client-0.1.1.dist-info/WHEEL
dex_k8s_client-0.1.1.dist-info/top_level.txt
dex_k8s_client-0.1.1.dist-info/RECORD
