Metadata-Version: 2.1
Name: dex-k8s-client
Version: 0.1.1
Summary: Python bindings for interacting with a Dex server running on Kubernetes.
Home-page: http://github.com/djtaylor/python-dex-k8s-client
Author: David Taylor
Author-email: djtaylor13@gmail.com
License: GPLv3
Keywords: grpc rpc api dex k8s kubernetes
Platform: UNKNOWN
Classifier: Development Status :: 3 - Alpha
Classifier: Environment :: Console
Classifier: License :: OSI Approved :: GNU General Public License v3 or later (GPLv3+)
Classifier: Natural Language :: English
Classifier: Operating System :: POSIX
Classifier: Programming Language :: Python
Classifier: Topic :: Software Development :: User Interfaces
Classifier: Topic :: Terminals
Requires-Dist: grpc-api-client
Requires-Dist: grpcio
Requires-Dist: grpcio-tools
Requires-Dist: passlib
Requires-Dist: bcrypt
Requires-Dist: requests
Requires-Dist: requests-oauthlib
Requires-Dist: pyyaml
Requires-Dist: pyjwt
Requires-Dist: cryptography
